bob/__init__.py
bob/application.py
bob/bacnet.py
bob/core.py
bob/enum.py
bob/functions.py
bob/introspection.py
bob/multimethods.py
bob/template.py
bob/connections/__init__.py
bob/connections/air.py
bob/connections/controlsignal.py
bob/connections/electricity.py
bob/connections/light.py
bob/connections/liquid.py
bob/connections/mechanical.py
bob/connections/naturalgas.py
bob/connections/network.py
bob/connections/occupancy.py
bob/connections/refrigerant.py
bob/equipment/__init__.py
bob/equipment/architectural/__init__.py
bob/equipment/architectural/door.py
bob/equipment/architectural/window.py
bob/equipment/control/__init__.py
bob/equipment/control/controller.py
bob/equipment/electricity/__init__.py
bob/equipment/electricity/distribution.py
bob/equipment/electricity/meter.py
bob/equipment/electricity/starter.py
bob/equipment/electricity/switch.py
bob/equipment/electricity/vfd.py
bob/equipment/hvac/__init__.py
bob/equipment/hvac/actuator.py
bob/equipment/hvac/airflowstation.py
bob/equipment/hvac/airhandlingunit.py
bob/equipment/hvac/boiler.py
bob/equipment/hvac/chiller.py
bob/equipment/hvac/coil.py
bob/equipment/hvac/compressor.py
bob/equipment/hvac/damper.py
bob/equipment/hvac/fan.py
bob/equipment/hvac/filter.py
bob/equipment/hvac/gas.py
bob/equipment/hvac/geothermal.py
bob/equipment/hvac/heatexchanger.py
bob/equipment/hvac/humidifier.py
bob/equipment/hvac/particlecounter.py
bob/equipment/hvac/pump.py
bob/equipment/hvac/scr.py
bob/equipment/hvac/stats.py
bob/equipment/hvac/tank.py
bob/equipment/hvac/triac.py
bob/equipment/hvac/valve.py
bob/equipment/hvac/vav.py
bob/equipment/lighting/__init__.py
bob/equipment/lighting/light.py
bob/equipment/network/__init__.py
bob/equipment/network/firewall.py
bob/equipment/network/switch.py
bob/externalreference/__init__.py
bob/externalreference/bacnet.py
bob/externalreference/timeseries.py
bob/producer/__init__.py
bob/producer/causality.py
bob/producer/g36.py
bob/producer/hvacspace.py
bob/producer/occupancy.py
bsit_bob-0.1.1.dist-info/licenses/LICENSE
bsit_bob-0.1.1.dist-info/METADATA
bsit_bob-0.1.1.dist-info/WHEEL
bsit_bob-0.1.1.dist-info/top_level.txt
bsit_bob-0.1.1.dist-info/RECORD
