Metadata-Version: 2.4
Name: bsit-bob
Version: 0.1.1
Summary: BACnet Semantic Interoperability Toolkit - Bob - Building Model Builder
Requires-Python: >=3.13
License-File: LICENSE
Requires-Dist: pyyaml>=6.0.2
Requires-Dist: rdflib>=7.1.4
Dynamic: license-file
